MANIFEST.in
README.rst
setup.py
django_icons_splashyicons.egg-info/PKG-INFO
django_icons_splashyicons.egg-info/SOURCES.txt
django_icons_splashyicons.egg-info/dependency_links.txt
django_icons_splashyicons.egg-info/requires.txt
django_icons_splashyicons.egg-info/top_level.txt
icons_splashyicons/__init__.py
icons_splashyicons/models.py
icons_splashyicons/static/icons/.noremove
icons_splashyicons/static/icons/splashyicons/add.png
icons_splashyicons/static/icons/splashyicons/add_outline.png
icons_splashyicons/static/icons/splashyicons/add_small.png
icons_splashyicons/static/icons/splashyicons/application_osx.png
icons_splashyicons/static/icons/splashyicons/application_osx_add.png
icons_splashyicons/static/icons/splashyicons/application_osx_down.png
icons_splashyicons/static/icons/splashyicons/application_osx_edit.png
icons_splashyicons/static/icons/splashyicons/application_osx_grow.png
icons_splashyicons/static/icons/splashyicons/application_osx_left.png
icons_splashyicons/static/icons/splashyicons/application_osx_locked.png
icons_splashyicons/static/icons/splashyicons/application_osx_new.png
icons_splashyicons/static/icons/splashyicons/application_osx_okay.png
icons_splashyicons/static/icons/splashyicons/application_osx_remove.png
icons_splashyicons/static/icons/splashyicons/application_osx_right.png
icons_splashyicons/static/icons/splashyicons/application_osx_share.png
icons_splashyicons/static/icons/splashyicons/application_osx_up.png
icons_splashyicons/static/icons/splashyicons/application_osx_warning.png
icons_splashyicons/static/icons/splashyicons/application_windows.png
icons_splashyicons/static/icons/splashyicons/application_windows_add.png
icons_splashyicons/static/icons/splashyicons/application_windows_down.png
icons_splashyicons/static/icons/splashyicons/application_windows_edit.png
icons_splashyicons/static/icons/splashyicons/application_windows_grow.png
icons_splashyicons/static/icons/splashyicons/application_windows_left.png
icons_splashyicons/static/icons/splashyicons/application_windows_locked.png
icons_splashyicons/static/icons/splashyicons/application_windows_new.png
icons_splashyicons/static/icons/splashyicons/application_windows_okay.png
